centrifuge_cli/__init__.py
centrifuge_cli/main.py
centrifuge_cli/policy.py
centrifuge_cli/stats.py
centrifuge_cli-0.9.1.dist-info/entry_points.txt
centrifuge_cli-0.9.1.dist-info/LICENSE
centrifuge_cli-0.9.1.dist-info/WHEEL
centrifuge_cli-0.9.1.dist-info/METADATA
centrifuge_cli-0.9.1.dist-info/RECORD
