Metadata-Version: 2.1
Name: centrifuge-cli
Version: 0.9.1
Summary: A command line utility for interacting with the Centrifuge Firmware Analysis Platform's REST API.
Home-page: https://www.refirmlabs.com
Keywords: firmware,security,centrifuge
Author: Peter Eacmen
Author-email: peacmen@refirmlabs.com
Requires-Python: >=3.9,<4.0
Classifier: Programming Language :: Python :: 3
Classifier: Programming Language :: Python :: 3.10
Classifier: Programming Language :: Python :: 3.9
Requires-Dist: Click (>=7.0,<8.0)
Requires-Dist: chevron (>=0.13.1,<0.14.0)
Requires-Dist: dateparser (>=0.7.2,<0.8.0)
Requires-Dist: pandas (>=1,<2)
Requires-Dist: pyyaml (>=5.3.1,<6.0.0)
Requires-Dist: requests (>=2.22,<3.0)
Project-URL: Repository, https://github.com/ReFirmLabs/centrifuge-cli
